wilt_amaze_slack_node/__init__.py
wilt_amaze_slack_node/exceptions.py
wilt_amaze_slack_node/py.typed
wilt_amaze_slack_node/tests.py
wilt_amaze_slack_node-0.1.1.dist-info/METADATA
wilt_amaze_slack_node-0.1.1.dist-info/WHEEL
wilt_amaze_slack_node-0.1.1.dist-info/licenses/LICENSE
wilt_amaze_slack_node-0.1.1.dist-info/RECORD
